dagwood/__init__.py
dagwood/http_codes.py
dagwood/logging_utils.py
dagwood/version.py
dagwood-2.0.0.dist-info/LICENSE
dagwood-2.0.0.dist-info/METADATA
dagwood-2.0.0.dist-info/WHEEL
dagwood-2.0.0.dist-info/top_level.txt
dagwood-2.0.0.dist-info/RECORD
