Metadata-Version: 2.1
Name: dagwood
Version: 2.0.0
Summary: Swiss-army knife for Python scripts. Includes logging, HTTP status codes, and more.
Home-page: https://github.com/heyodai/dagwood
Author: Odai Athamneh
Author-email: heyodai@gmail.com
License: UNKNOWN
Platform: UNKNOWN
License-File: LICENSE
